spec/__init__.py
spec/cli/__init__.py
spec/cli/spec.py
spec/compiler/__init__.py
spec/compiler/compiler.py
spec/compiler/parser.py
spec/core/__init__.py
spec/core/loader.py
specwright-0.3.1.dist-info/licenses/LICENSE
specwright-0.3.1.dist-info/METADATA
specwright-0.3.1.dist-info/WHEEL
specwright-0.3.1.dist-info/entry_points.txt
specwright-0.3.1.dist-info/top_level.txt
specwright-0.3.1.dist-info/RECORD
