Metadata-Version: 2.4
Name: specwright
Version: 0.3.1
Summary: The architect of agentic workflows. Defines, validates, and executes AIPs.
Author-email: Benjamin Armstrong <bfarmstrong@example.com>
License: MIT
Project-URL: Repository, https://github.com/bfarmstrong/specwright
Project-URL: Issues, https://github.com/bfarmstrong/specwright/issues
Project-URL: Documentation, https://specwright.dev
Project-URL: Homepage, https://specwright.dev
Keywords: agentic,orchestration,governance,agentsway,implementation-plans,specwright,aip,tiered-governance,compliance,iso42001,nist-ai-rmf
Classifier: Development Status :: 3 - Alpha
Classifier: Intended Audience :: Developers
Classifier: License :: OSI Approved :: MIT License
Classifier: Programming Language :: Python :: 3.12
Classifier: Topic :: Software Development :: Quality Assurance
Classifier: Topic :: Software Development :: Code Generators
Requires-Python: >=3.12
License-File: LICENSE
Requires-Dist: pyyaml>=6.0.1
Requires-Dist: jsonschema>=4.20.0
Requires-Dist: typer>=0.9.0
Requires-Dist: jinja2>=3.1.0
Provides-Extra: dev
Requires-Dist: ruff>=0.1.0; extra == "dev"
Requires-Dist: mypy>=1.7.0; extra == "dev"
Requires-Dist: types-pyyaml>=6.0.12; extra == "dev"
Dynamic: license-file
